{
  "topic": "tourism",
  "vintageRange": {
    "start": 2010,
    "end": 2024
  },
  "sources": [
    {
      "id": "CDOR_LODGING",
      "agency": "Colorado Department of Revenue",
      "dataset": "Lodging Tax Reports",
      "endpoint": "https://data.colorado.gov/resource/5xyk-vsx9.json",
      "lastPulled": "2026-05-04"
    },
    {
      "id": "QCEW_TOURISM",
      "agency": "U.S. Bureau of Labor Statistics",
      "dataset": "QCEW NAICS 71 (Arts/Ent) + NAICS 72 (Accommodation/Food)",
      "endpoint": "https://data.bls.gov/cew/data/api",
      "lastPulled": "2026-05-04"
    },
    {
      "id": "BTS_T100",
      "agency": "U.S. Bureau of Transportation Statistics",
      "dataset": "T-100 Domestic Segment Data",
      "endpoint": "https://www.transtats.bts.gov/",
      "lastPulled": "2026-05-04"
    },
    {
      "id": "RFTA_YIR",
      "agency": "Roaring Fork Transportation Authority",
      "dataset": "Annual Year-in-Review",
      "endpoint": "https://www.rfta.com/public-documents/",
      "lastPulled": "2026-05-04"
    }
  ],
  "state": {
    "fips": "08",
    "name": "Colorado",
    "latest": null,
    "trend": {}
  },
  "counties": [
    {
      "fips": "037",
      "geoid": "08037",
      "name": "Eagle County",
      "latest": null,
      "trend": {}
    },
    {
      "fips": "045",
      "geoid": "08045",
      "name": "Garfield County",
      "latest": null,
      "trend": {}
    },
    {
      "fips": "077",
      "geoid": "08077",
      "name": "Mesa County",
      "latest": null,
      "trend": {}
    },
    {
      "fips": "097",
      "geoid": "08097",
      "name": "Pitkin County",
      "latest": null,
      "trend": {}
    }
  ],
  "places": [
    {
      "zip": "81601",
      "name": "Glenwood Springs",
      "kind": "place",
      "placeGeoid": "0830780",
      "countyGeoid": "08045",
      "countyName": "Garfield County",
      "latest": null,
      "trend": {}
    },
    {
      "zip": "81611",
      "name": "Aspen",
      "kind": "place",
      "placeGeoid": "0803620",
      "countyGeoid": "08097",
      "countyName": "Pitkin County",
      "latest": null,
      "trend": {}
    },
    {
      "zip": "81615",
      "name": "Snowmass Village",
      "kind": "place",
      "placeGeoid": "0871755",
      "countyGeoid": "08097",
      "countyName": "Pitkin County",
      "latest": null,
      "trend": {}
    },
    {
      "zip": "81621",
      "name": "Basalt",
      "kind": "place",
      "placeGeoid": "0804935",
      "countyGeoid": "08097",
      "countyName": "Pitkin County",
      "latest": null,
      "trend": {}
    },
    {
      "zip": "81623",
      "name": "Carbondale",
      "kind": "place",
      "placeGeoid": "0812045",
      "countyGeoid": "08045",
      "countyName": "Garfield County",
      "latest": null,
      "trend": {}
    },
    {
      "zip": "81630",
      "name": "De Beque",
      "kind": "place",
      "placeGeoid": "0819355",
      "countyGeoid": "08045",
      "countyName": "Garfield County",
      "latest": null,
      "trend": {}
    },
    {
      "zip": "81635",
      "name": "Parachute",
      "kind": "place",
      "placeGeoid": "0857400",
      "countyGeoid": "08045",
      "countyName": "Garfield County",
      "latest": null,
      "trend": {}
    },
    {
      "zip": "81647",
      "name": "New Castle",
      "kind": "place",
      "placeGeoid": "0853395",
      "countyGeoid": "08045",
      "countyName": "Garfield County",
      "latest": null,
      "trend": {}
    },
    {
      "zip": "81650",
      "name": "Rifle",
      "kind": "place",
      "placeGeoid": "0864255",
      "countyGeoid": "08045",
      "countyName": "Garfield County",
      "latest": null,
      "trend": {}
    },
    {
      "zip": "81652",
      "name": "Silt",
      "kind": "place",
      "placeGeoid": "0870195",
      "countyGeoid": "08045",
      "countyName": "Garfield County",
      "latest": null,
      "trend": {}
    },
    {
      "zip": "81654",
      "name": "Old Snowmass",
      "kind": "zcta",
      "placeGeoid": null,
      "countyGeoid": "08097",
      "countyName": "Pitkin County",
      "latest": null,
      "trend": {}
    }
  ]
}